itty.py
itty-0.8.2.dist-info/DESCRIPTION.rst
itty-0.8.2.dist-info/METADATA
itty-0.8.2.dist-info/pydist.json
itty-0.8.2.dist-info/RECORD
itty-0.8.2.dist-info/top_level.txt
itty-0.8.2.dist-info/WHEEL
