Metadata-Version: 1.1
Name: itty
Version: 0.8.2
Summary: The itty-bitty Python web framework.
Home-page: http://github.com/toastdriven/itty/
Author: Daniel Lindsley
Author-email: daniel@toastdriven.com
License: BSD
Platform: UNKNOWN
Classifier: License :: OSI Approved :: BSD License
